{
  "@context": "http://schema.org/",
  "@type": "Clip",
  "name": "田んぼが育む伊賀の牛",
  "description": "詳細: 三重県北西部の伊賀地方は田んぼが広がる米どころ。田んぼと関係の深いもうひとつの伊賀の味が、特産の伊賀牛。近年人気のブランドで流通量が少なく幻の牛肉とも呼ばれます。かつて伊賀では田んぼを耕す牛は一家に一頭が当たり前でした。明治時代に入り肉食が解禁されると、年を重ねた農耕牛を引き取り食用として売り買いする馬喰（ばくろう）が盛んになります。第二次大戦後、馬喰の子孫など個人経営の牧場が、小規模ながら質の良い肉牛を育て現在の伊賀牛ブランドにつながっていきます。伊賀で三代続く畜産農家の奥田能己さんは、昔ながらの牛と田んぼのつながりを継承し餌は地元の米農家からもらったもみ殻や米ぬか、稲わらを使います。牛の排泄物は堆肥にして米農家に届けます。田んぼが牛を育て、牛が米を育む。持ちつ持たれつの歴史が伊賀の里を豊かにしてきました。\\n（この動画は、２０１９年に放送したものです。）\\n",
  "spatial": {
    "@type": "AdministrativeArea",
    "name": "?"
  }
}