{
  "@context": "http://schema.org/",
  "@id": "https://jpsearch.go.jp/data/michi-D0004380100_00000",
  "@type": "Clip",
  "name": "猫小節",
  "description": "詳細: 「まや」とは猫のこと。猫小節（まやぐゎぶし・まやぐぁーぶし）は日本最西端の島「与那国島」に伝わる民謡で、「与那国のまやぐゎ節」とも呼ばれています。\\n琉球王国時代、島に派遣されていた首里王府の役人や支配階級を、歌詞の中で「猫」や「犬」にたとえて揶揄しています。軽快なメロディーをもち、韻を踏んだ言葉遊びの要素の強い唄です。\\n【歌詞】\\n与那国の猫小　うやんちゅだましぬやからはり　\\n二才だましぬ　やから崎浜ヨー主ぬまいはり\\nヨーヌヨーシュヌマイハリシターリヨーンゾ　ハイヤササ\\n\\n西からや大嶺主　東からや八重山主ぬはり　\\n真中からみかかぬとばいきてぃはいりきたんとぅんはり\\n ヨーヌヨーシュヌマイハリシターリヨーンゾ　ハイヤササ\\n\\n大月とうふ太陽と上がる目やひとちはり\\n波座真の主と我とぅの仲やひとちはり\\nヨーヌヨーシュヌマイハリシターリヨーンゾ　ハイヤササ\\n（－以下略－）",
  "spatial": [
    {
      "@id": "https://jpsearch.go.jp/entity/place/沖縄"
    },
    "都道府県: 沖縄県",
    "住所: 八重山郡与那国町"
  ]
}